pygal_maps_ru/__init__.py
pygal_maps_ru/maps.py
pygal_maps_ru/russia.svg
pygal_maps_ru-1.0.1.1.dist-info/LICENSE
pygal_maps_ru-1.0.1.1.dist-info/METADATA
pygal_maps_ru-1.0.1.1.dist-info/WHEEL
pygal_maps_ru-1.0.1.1.dist-info/entry_points.txt
pygal_maps_ru-1.0.1.1.dist-info/top_level.txt
pygal_maps_ru-1.0.1.1.dist-info/RECORD
